{
  "version": "3.84.31647.0",
  "course_id": "6A9MOiBruxg",
  "title": "Giving Criticism",
  "thumbnail": "story_content/thumbnail.jpg",
  "scenes": [
    {
      "title": "Knowledge Check"
    }
  ],
  "slides": [
    {
      "id": "5gNPC0ClZ1S",
      "title": "Beginning",
      "scene_index": "1.1"
    },
    {
      "id": "6VDH4OufTiE",
      "title": "Giving Constructive Feedback",
      "scene_index": "1.2"
    },
    {
      "id": "5vLvrZjPzZy",
      "title": "Giving Constructive Feedback",
      "scene_index": "1.3"
    },
    {
      "id": "5VfDHwKEbi6",
      "title": "Giving Constructive Feedback",
      "scene_index": "1.4"
    },
    {
      "id": "5joRHHKDezd",
      "title": "Giving Constructive Feedback",
      "scene_index": "1.5"
    },
    {
      "id": "5tCwtReed31",
      "title": "End",
      "scene_index": "1.6"
    }
  ],
  "player": {
    "name": "unified",
    "width": 980,
    "height": 560
  },
  "stage": {
    "width": 960,
    "height": 540
  }
}